dnacentercli/__init__.py
dnacentercli/_metadata.py
dnacentercli/cli/__init__.py
dnacentercli/cli/utils/__init__.py
dnacentercli/cli/utils/click_spinner.py
dnacentercli/cli/utils/print.py
dnacentercli/cli/utils/spinner.py
dnacentercli/cli/v1_2_10/__init__.py
dnacentercli/cli/v1_2_10/clients.py
dnacentercli/cli/v1_2_10/command_runner.py
dnacentercli/cli/v1_2_10/devices.py
dnacentercli/cli/v1_2_10/fabric_wired.py
dnacentercli/cli/v1_2_10/file.py
dnacentercli/cli/v1_2_10/network_discovery.py
dnacentercli/cli/v1_2_10/networks.py
dnacentercli/cli/v1_2_10/non_fabric_wireless.py
dnacentercli/cli/v1_2_10/path_trace.py
dnacentercli/cli/v1_2_10/pnp.py
dnacentercli/cli/v1_2_10/site_profile.py
dnacentercli/cli/v1_2_10/sites.py
dnacentercli/cli/v1_2_10/swim.py
dnacentercli/cli/v1_2_10/tag.py
dnacentercli/cli/v1_2_10/task.py
dnacentercli/cli/v1_2_10/template_programmer.py
dnacentercli/cli/v1_3_0/__init__.py
dnacentercli/cli/v1_3_0/clients.py
dnacentercli/cli/v1_3_0/command_runner.py
dnacentercli/cli/v1_3_0/devices.py
dnacentercli/cli/v1_3_0/fabric_wired.py
dnacentercli/cli/v1_3_0/file.py
dnacentercli/cli/v1_3_0/network_discovery.py
dnacentercli/cli/v1_3_0/networks.py
dnacentercli/cli/v1_3_0/non_fabric_wireless.py
dnacentercli/cli/v1_3_0/path_trace.py
dnacentercli/cli/v1_3_0/pnp.py
dnacentercli/cli/v1_3_0/site_profile.py
dnacentercli/cli/v1_3_0/sites.py
dnacentercli/cli/v1_3_0/swim.py
dnacentercli/cli/v1_3_0/tag.py
dnacentercli/cli/v1_3_0/task.py
dnacentercli/cli/v1_3_0/template_programmer.py
dnacentercli/cli/v1_3_1/__init__.py
dnacentercli/cli/v1_3_1/application_policy.py
dnacentercli/cli/v1_3_1/clients.py
dnacentercli/cli/v1_3_1/command_runner.py
dnacentercli/cli/v1_3_1/configuration_templates.py
dnacentercli/cli/v1_3_1/device_onboarding_pnp.py
dnacentercli/cli/v1_3_1/devices.py
dnacentercli/cli/v1_3_1/event_management.py
dnacentercli/cli/v1_3_1/fabric_wired.py
dnacentercli/cli/v1_3_1/file.py
dnacentercli/cli/v1_3_1/issues.py
dnacentercli/cli/v1_3_1/network_discovery.py
dnacentercli-2.1.1.dist-info/LICENSE
dnacentercli-2.1.1.dist-info/WHEEL
dnacentercli-2.1.1.dist-info/METADATA
dnacentercli-2.1.1.dist-info/RECORD
